[
    {
      "username": "Lili",
      "email": "lils@mail.com",
      "_id": "64bacc201284d46e96bd8ba7",
      "password": "123456"
    },
    {
      "username": "Emerald",
      "email": "ems@mail.com",
      "_id": "64bacc361284d46e96bd8ba9",
      "password": "123456"
    },
    {
      "username": "Jonathan",
      "email": "Jonathan@mail.com",
      "_id": "64bacc501284d46e96bd8bab",
      "password": "123456"
    },
    {
      "username": "Rosa",
      "email": "rosa@mail.com",
      "_id": "64bacc5d1284d46e96bd8bad",
      "password": "123456"
    },
    {
      "username": "joe",
      "email": "joe@mail.com",
      "_id": "64bacc681284d46e96bd8baf",
      "password": "123456"
    },
    {
      "username": "ben",
      "email": "ben@mail.com",
      "_id": "64bacc781284d46e96bd8bb1",
      "password": "123456"
    },
    {
      "username": "peter",
      "email": "peter@mail.com",
      "_id": "64bacc851284d46e96bd8bb3",
      "password": "123456"
    },
    {
      "username": "Tam",
      "email": "Tammy@mail.com",
      "_id": "64bacc8f1284d46e96bd8bb5",
      "password": "123456"
    },
    {
      "username": "dime",
      "email": "dime@mail.com",
      "_id": "64bacc9e1284d46e96bd8bb7",
      "password": "123456"
    },
    {
      "username": "dawg",
      "email": "dd@mail.com",
      "_id": "64baccba1284d46e96bd8bb9",
      "password": "123456"
    },
    {
      "username": "Kevin",
      "email": "gates@mail.com",
      "_id": "64baccc81284d46e96bd8bbb",
      "password": "123456"
    },
    {
      "username": "Bill",
      "email": "Obs@mail.com",
      "_id": "64baccdc1284d46e96bd8bbd",
      "password": "123456"
    },
    {
      "username": "Avatar",
      "email": "moview@mail.com",
      "_id": "64bacce71284d46e96bd8bbf",
      "password": "123456"
    },
    {
      "username": "ps2",
      "email": "ps1@mail.com",
      "_id": "64baccf71284d46e96bd8bc1",
      "password": "123456"
    },
    {
      "username": "jackie",
      "email": "chan@mail.com",
      "_id": "64bacd0a1284d46e96bd8bc3",
      "password": "123456"
    },
    {
      "username": "Tom",
      "email": "thams@mail.com",
      "_id": "64bacd2f1284d46e96bd8bc6",
      "password": "123456"
    },
    {
      "username": "Big",
      "email": "big@mail.com",
      "_id": "64bacd3f1284d46e96bd8bc8",
      "password": "123456"
    }
  ]